keepa/__init__.py
keepa/constants.py
keepa/keepa_async.py
keepa/keepa_sync.py
keepa/plotting.py
keepa/py.typed
keepa/query_keys.py
keepa/utils.py
keepa/models/domain.py
keepa/models/product_params.py
keepa/models/status.py
keepa-1.4.3.dist-info/licenses/LICENSE
keepa-1.4.3.dist-info/WHEEL
keepa-1.4.3.dist-info/METADATA
keepa-1.4.3.dist-info/RECORD
