Metadata-Version: 2.4
Name: keepa
Version: 1.4.3
Summary: Interfaces with keepa.com's API.
Keywords: keepa
Author-email: Alex Kaszynski <akascap@gmail.com>
Requires-Python: >=3.10
Classifier: Development Status :: 5 - Production/Stable
Classifier: Intended Audience :: End Users/Desktop
Classifier: Topic :: Database :: Front-Ends
Classifier: License :: OSI Approved :: Apache Software License
Classifier: Programming Language :: Python :: 3.10
Classifier: Programming Language :: Python :: 3.11
Classifier: Programming Language :: Python :: 3.12
Classifier: Programming Language :: Python :: 3.13
Classifier: Programming Language :: Python :: 3.14
License-File: LICENSE
Requires-Dist: numpy >=1.9.3
Requires-Dist: requests >=2.2
Requires-Dist: tqdm
Requires-Dist: aiohttp
Requires-Dist: pandas <= 3.0
Requires-Dist: pydantic
Requires-Dist: sphinx==9.1.0 ; extra == "doc"
Requires-Dist: pydata-sphinx-theme==0.16.1 ; extra == "doc"
Requires-Dist: numpydoc==1.10.0 ; extra == "doc"
Requires-Dist: matplotlib ; extra == "test"
Requires-Dist: pandas ; extra == "test"
Requires-Dist: pytest-asyncio ; extra == "test"
Requires-Dist: pytest-cov ; extra == "test"
Requires-Dist: pytest ; extra == "test"
Requires-Dist: pytest-rerunfailures ; extra == "test"
Project-URL: Documentation, https://keepaapi.readthedocs.io/en/latest/
Project-URL: Source, https://github.com/akaszynski/keepa
Provides-Extra: doc
Provides-Extra: test
